xiaomipassive/__init__.py
xiaomipassive/xiaomipassive.py
xiaomipassive/scripts/__init__.py
xiaomipassive/scripts/tools.py
xiaomipassive-2023.2.6.dist-info/LICENSE
xiaomipassive-2023.2.6.dist-info/METADATA
xiaomipassive-2023.2.6.dist-info/WHEEL
xiaomipassive-2023.2.6.dist-info/entry_points.txt
xiaomipassive-2023.2.6.dist-info/top_level.txt
xiaomipassive-2023.2.6.dist-info/RECORD
