Metadata-Version: 2.1
Name: xiaomipassive
Version: 2023.2.6
Summary: MiFlora and LYWSD02 passive scanner
Author-email: Alain <afer921@mailfence.com>
License: MIT License
Project-URL: Homepage, https://github.com/afer92/xiaomipassive
Project-URL: Bug Tracker, https://github.com/afer92/xiaomipassive/issues
Keywords: home,automation,xiaomi,LYWSD02,LYWSD03,Flower care
Classifier: Development Status :: 5 - Production/Stable
Classifier: Intended Audience :: End Users/Desktop
Classifier: Intended Audience :: Developers
Classifier: License :: OSI Approved :: MIT License
Classifier: Operating System :: OS Independent
Classifier: Programming Language :: Python :: 3.9
Classifier: Programming Language :: Python :: 3.10
Classifier: Topic :: Home Automation
Requires-Python: >=3.9.0
License-File: LICENSE
Requires-Dist: bleak
Requires-Dist: construct
Requires-Dist: pip (>=21.0)
